prajyotKaPack/__init__.py
prajyotKaPack-1.1.dist-info/LICENSE.txt
prajyotKaPack-1.1.dist-info/METADATA
prajyotKaPack-1.1.dist-info/WHEEL
prajyotKaPack-1.1.dist-info/top_level.txt
prajyotKaPack-1.1.dist-info/RECORD
